Metadata-Version: 2.1
Name: django-smart-selects
Version: 1.7.2
Summary: Django application to handle chained model fields.
Home-page: https://github.com/jazzband/django-smart-selects
Author: Patrick Lauber
Author-email: digi@treepy.com
Classifier: Programming Language :: Python :: 3
Classifier: Programming Language :: Python :: 3.8
Classifier: Programming Language :: Python :: 3.9
Classifier: Programming Language :: Python :: 3.10
Classifier: Programming Language :: Python :: 3.11
Classifier: Programming Language :: Python :: 3.12
Classifier: Framework :: Django
Classifier: Framework :: Django :: 3.2
Classifier: Framework :: Django :: 4.0
Classifier: Framework :: Django :: 4.1
Classifier: Framework :: Django :: 4.2
Classifier: Framework :: Django :: 5.0
Requires-Python: >=3.8
License-File: LICENSE
License-File: AUTHORS
Requires-Dist: django>=3.2
